{
	"description": "项目配置文件。",
	"packOptions": {
		"ignore": []
	},
	"setting": {
		"urlCheck": false,
		"es6": true,
		"postcss": true,
		"minified": true,
		"newFeature": true,
		"nodeModules": false
	},
	"compileType": "miniprogram",
	"libVersion": "2.2.1",
	"appid": "wxf01e1fc0768c59ba",
	"projectname": "%E5%B0%8F%E9%BA%A6%E8%8A%AC%E7%83%98%E7%84%99%E5%B0%8F%E5%BA%97",
	"isGameTourist": false,
	"condition": {
		"search": {
			"current": -1,
			"list": []
		},
		"conversation": {
			"current": -1,
			"list": []
		},
		"game": {
			"currentL": -1,
			"list": []
		},
		"miniprogram": {
			"current": -1,
			"list": []
		}
	}
}